nextgraph-0.1a1.dev2.dist-info/METADATA
nextgraph-0.1a1.dev2.dist-info/WHEEL
nextgraph/__init__.py
nextgraph/nextgraph.cpython-37m-darwin.so
nextgraph-0.1a1.dev2.dist-info/RECORD
