Metadata-Version: 2.4
Name: nextgraph
Version: 0.1a1.dev2
Classifier: Programming Language :: Rust
Classifier: Programming Language :: Python :: Implementation :: CPython
Classifier: Programming Language :: Python :: Implementation :: PyPy
Summary: NextGraph brings about the convergence of P2P and Semantic Web technologies, towards a decentralized, secure and privacy-preserving cloud, based on CRDTs.
Keywords: crdt,e2ee,local-first,p2p,semantic-web
Home-Page: https://nextgraph.org
Author: Niko PLP <niko@nextgraph.org>
Author-email: Niko PLP <niko@nextgraph.org>
License: MIT/Apache-2.0
Requires-Python: >=3.7.3
Project-URL: Source Code, https://git.nextgraph.org/NextGraph/nextgraph-rs
